Metadata-Version: 1.0
Name: zeitapi
Version: 0.2
Summary: Module for communication with Zeit Devices
Home-page: http://www.zeit.com.mx
Author: ITEK
Author-email: noemail@itek.mx
License: MIT
Platform: UNKNOWN
